aldkit/__init__.py
aldkit/ald.py
aldkit/ald_help.py
aldkit/ald_input.py
aldkit/ald_pbs.py
aldkit/tools.py
aldkit/aldcodes/cluster_settings.py
aldkit/aldcodes/dfpt.py
aldkit/aldcodes/dft.py
aldkit/aldcodes/isotopesData.pickle
aldkit/aldcodes/parameters_convergence.py
aldkit/pseudos/LDA_ONCV/Ag.UPF
aldkit/pseudos/LDA_ONCV/Al.UPF
aldkit/pseudos/LDA_ONCV/Ar.UPF
aldkit/pseudos/LDA_ONCV/As.UPF
aldkit/pseudos/LDA_ONCV/Au.UPF
aldkit/pseudos/LDA_ONCV/B.UPF
aldkit/pseudos/LDA_ONCV/Ba.UPF
aldkit/pseudos/LDA_ONCV/Be.UPF
aldkit/pseudos/LDA_ONCV/Bi.UPF
aldkit/pseudos/LDA_ONCV/Br.UPF
aldkit/pseudos/LDA_ONCV/C.UPF
aldkit/pseudos/LDA_ONCV/Ca.UPF
aldkit/pseudos/LDA_ONCV/Cd.UPF
aldkit/pseudos/LDA_ONCV/Cl.UPF
aldkit/pseudos/LDA_ONCV/Co.UPF
aldkit/pseudos/LDA_ONCV/Cr.UPF
aldkit/pseudos/LDA_ONCV/Cs.UPF
aldkit/pseudos/LDA_ONCV/Cu.UPF
aldkit/pseudos/LDA_ONCV/F.UPF
aldkit/pseudos/LDA_ONCV/Fe.UPF
aldkit/pseudos/LDA_ONCV/Ga.UPF
aldkit/pseudos/LDA_ONCV/Ge.UPF
aldkit/pseudos/LDA_ONCV/H.UPF
aldkit/pseudos/LDA_ONCV/He.UPF
aldkit/pseudos/LDA_ONCV/Hf.UPF
aldkit/pseudos/LDA_ONCV/Hg.UPF
aldkit/pseudos/LDA_ONCV/I.UPF
aldkit/pseudos/LDA_ONCV/In.UPF
aldkit/pseudos/LDA_ONCV/Ir.UPF
aldkit/pseudos/LDA_ONCV/K.UPF
aldkit/pseudos/LDA_ONCV/Kr.UPF
aldkit/pseudos/LDA_ONCV/Li.UPF
aldkit/pseudos/LDA_ONCV/Mg.UPF
aldkit/pseudos/LDA_ONCV/Mn.UPF
aldkit/pseudos/LDA_ONCV/Mo.UPF
aldkit/pseudos/LDA_ONCV/N.UPF
aldkit/pseudos/LDA_ONCV/Na.UPF
aldkit/pseudos/LDA_ONCV/Nb.UPF
aldkit/pseudos/LDA_ONCV/Ne.UPF
aldkit/pseudos/LDA_ONCV/Ni.UPF
aldkit/pseudos/LDA_ONCV/O.UPF
aldkit/pseudos/LDA_ONCV/Os.UPF
aldkit/pseudos/LDA_ONCV/P.UPF
aldkit/pseudos/LDA_ONCV/Pb.UPF
aldkit/pseudos/LDA_ONCV/Pd.UPF
aldkit/pseudos/LDA_ONCV/Po.UPF
aldkit/pseudos/LDA_ONCV/Pt.UPF
aldkit/pseudos/LDA_ONCV/Rb.UPF
aldkit/pseudos/LDA_ONCV/Re.UPF
aldkit/pseudos/LDA_ONCV/Rh.UPF
aldkit/pseudos/LDA_ONCV/Rn.UPF
aldkit/pseudos/LDA_ONCV/Ru.UPF
aldkit/pseudos/LDA_ONCV/S.UPF
aldkit/pseudos/LDA_ONCV/Sb.UPF
aldkit/pseudos/LDA_ONCV/Sc.UPF
aldkit/pseudos/LDA_ONCV/Se.UPF
aldkit-1.1.13.dist-info/METADATA
aldkit-1.1.13.dist-info/WHEEL
aldkit-1.1.13.dist-info/entry_points.txt
aldkit-1.1.13.dist-info/top_level.txt
aldkit-1.1.13.dist-info/RECORD
