Metadata-Version: 2.1
Name: aldkit
Version: 1.1.13
Summary: Parser for anharmonic lattice dynamics package developed by Prof. Ankit Jain.
Home-page: UNKNOWN
Author: Harish PVV
Author-email: harishpvv@gmail.com
License: MIT
Keywords: ald
Platform: UNKNOWN
Classifier: Programming Language :: Python :: 3
Classifier: License :: OSI Approved :: MIT License
Classifier: Operating System :: OS Independent
Requires-Dist: ase
Requires-Dist: spglib
